casho/__init__.py
casho/mylibrary/__init__.py
casho/mylibrary/apps.py
casho/mylibrary/errors/__init__.py
casho/mylibrary/errors/custom_error.py
casho/mylibrary/errors/database_connection_error.py
casho/mylibrary/middlewares/__init__.py
casho/mylibrary/middlewares/errorhandler.py
casho/mylibrary/middlewares/healthcheck.py
cashooo-1.1.3.dist-info/METADATA
cashooo-1.1.3.dist-info/WHEEL
cashooo-1.1.3.dist-info/top_level.txt
cashooo-1.1.3.dist-info/RECORD
